assistant_chat_check/__init__.py
assistant_chat_check/main.py
assistant_chat_check/tf_config.py
assistant_chat_check-0.0.3.dist-info/METADATA
assistant_chat_check-0.0.3.dist-info/WHEEL
assistant_chat_check-0.0.3.dist-info/entry_points.txt
assistant_chat_check-0.0.3.dist-info/top_level.txt
assistant_chat_check-0.0.3.dist-info/RECORD
